[
  {
    "id": "mapa",
    "name": "Mapa",
    "description": "Stará mapa do Království víl",
    "portable": true,
    "usable": true
  },
  {
    "id": "kniha",
    "name": "Kniha",
    "description": "Stará kniha v kůži",
    "portable": true,
    "usable": false
  },
  {
    "id": "mec",
    "name": "Meč",
    "description": "Ostrý meč na obranu proti šelmám",
    "portable": true,
    "usable": true
  },
  {
    "id": "klic",
    "name": "Klíč",
    "description": "Zlatý klíč k bráně Království víl",
    "portable": true,
    "usable": true
  }
]
